unit_of_time/__init__.py
unit_of_time/_version.py
unit_of_time-0.3.0.0.dist-info/LICENSE
unit_of_time-0.3.0.0.dist-info/METADATA
unit_of_time-0.3.0.0.dist-info/WHEEL
unit_of_time-0.3.0.0.dist-info/top_level.txt
unit_of_time-0.3.0.0.dist-info/RECORD
