Metadata-Version: 2.1
Name: unit-of-time
Version: 0.3.0.0
Summary: Representing years, quarters, months, weeks and days as integers
Home-page: https://github.com/hapytex/unit_of_time/
Author: Willem Van Onsem
Author-email: Willem Van Onsem <yourfriends@hapytex.eu>
License: BSD-3-Clause
Classifier: Intended Audience :: Developers
Classifier: License :: OSI Approved :: BSD License
Classifier: Operating System :: OS Independent
Classifier: Programming Language :: Python
Classifier: Programming Language :: Python :: 3
Classifier: Programming Language :: Python :: 3 :: Only
Classifier: Programming Language :: Python :: 3.10
Classifier: Programming Language :: Python :: 3.11
Classifier: Programming Language :: Python :: 3.12
Requires-Python: >=3.8
License-File: LICENSE
